LICENSE
README.md
setup.py
flask_p.egg-info/PKG-INFO
flask_p.egg-info/SOURCES.txt
flask_p.egg-info/dependency_links.txt
flask_p.egg-info/requires.txt
flask_p.egg-info/top_level.txt
flask_projects/__init__.py
flask_projects/convension.py
flask_projects/core/__init__.py
flask_projects/core/order/__init__.py
flask_projects/core/order/executor.py
flask_projects/core/order/unity/__init__.py
flask_projects/core/order/unity/run.py
flask_projects/core/order/unity/shell.py
flask_projects/core/proj/__init__.py
flask_projects/core/proj/abs.py
flask_projects/core/proj/project.py
flask_projects/core/vars/__init__.py
flask_projects/core/vars/abs.py
flask_projects/core/vars/application.py
flask_projects/core/vars/extends.py
flask_projects/core/vars/http.py
flask_projects/core/vars/info.py
flask_projects/core/vars/others.py
flask_projects/default/__init__.py
flask_projects/default/app/__init__.py
flask_projects/default/app/factory.py
flask_projects/default/business/__init__.py
flask_projects/default/configuration/NameFactory.py
flask_projects/default/configuration/__init__.py
flask_projects/default/configuration/convention.py
flask_projects/default/configuration/plan_1/__init__.py
flask_projects/default/configuration/plan_default/__init__.py
flask_projects/default/configuration/plan_default/container.py
flask_projects/default/configuration/plan_default/logic.py
flask_projects/default/configuration/plan_default/scanner.py
flask_projects/default/middle/NameFactory.py
flask_projects/default/middle/__init__.py
flask_projects/default/middle/convention.py
flask_projects/default/middle/plan_0/__init__.py
flask_projects/default/middle/plan_0/container.py
flask_projects/default/middle/plan_0/logic.py
flask_projects/default/middle/plan_0/scanner.py
flask_projects/default/resource/__init__.py
flask_projects/default/router/NameFactory.py
flask_projects/default/router/__init__.py
flask_projects/default/router/convention.py
flask_projects/default/router/plan_0/__init__.py
flask_projects/default/router/plan_0/container.py
flask_projects/default/router/plan_0/logic.py
flask_projects/default/router/plan_0/order.py
