Metadata-Version: 2.1
Name: flask-p
Version: 0.0.2
Summary: flask projects系列快速开发手脚架核心
Home-page: https://github.com/ababbabbb/flask_project_core
Author: bichuantao
Author-email: 17826066203@163.com
License: MIT
Keywords: python,flask,projects,Rapid development
Requires-Python: >=3.6
License-File: LICENSE
Requires-Dist: flask
